MANIFEST.in
leveldb_ext.cc
leveldb_ext.h
leveldb_object.cc
setup.py
./snappy/snappy-c.cc
./snappy/snappy-sinksource.cc
./snappy/snappy-stubs-internal.cc
./snappy/snappy.cc
clang-c/include/clang-c/CXCompilationDatabase.h
clang-c/include/clang-c/CXString.h
clang-c/include/clang-c/Index.h
clang-c/include/clang-c/Platform.h
clang-c/lib/libclang.so
ctrlk/__init__.py
ctrlk/client_api.py
ctrlk/ctrlk_server.py
ctrlk/indexer.cpp
ctrlk/indexer.h
ctrlk/project.py
ctrlk/search.py
ctrlk.egg-info/PKG-INFO
ctrlk.egg-info/SOURCES.txt
ctrlk.egg-info/dependency_links.txt
ctrlk.egg-info/requires.txt
ctrlk.egg-info/top_level.txt
leveldb/db/autocompact_test.cc
leveldb/db/builder.cc
leveldb/db/builder.h
leveldb/db/c.cc
leveldb/db/corruption_test.cc
leveldb/db/db_bench.cc
leveldb/db/db_impl.cc
leveldb/db/db_impl.h
leveldb/db/db_iter.cc
leveldb/db/db_iter.h
leveldb/db/db_test.cc
leveldb/db/dbformat.cc
leveldb/db/dbformat.h
leveldb/db/dbformat_test.cc
leveldb/db/filename.cc
leveldb/db/filename.h
leveldb/db/filename_test.cc
leveldb/db/leveldb_main.cc
leveldb/db/log_format.h
leveldb/db/log_reader.cc
leveldb/db/log_reader.h
leveldb/db/log_test.cc
leveldb/db/log_writer.cc
leveldb/db/log_writer.h
leveldb/db/memtable.cc
leveldb/db/memtable.h
leveldb/db/repair.cc
leveldb/db/skiplist.h
leveldb/db/skiplist_test.cc
leveldb/db/snapshot.h
leveldb/db/table_cache.cc
leveldb/db/table_cache.h
leveldb/db/version_edit.cc
leveldb/db/version_edit.h
leveldb/db/version_edit_test.cc
leveldb/db/version_set.cc
leveldb/db/version_set.h
leveldb/db/version_set_test.cc
leveldb/db/write_batch.cc
leveldb/db/write_batch_internal.h
leveldb/db/write_batch_test.cc
leveldb/include/leveldb/c.h
leveldb/include/leveldb/cache.h
leveldb/include/leveldb/comparator.h
leveldb/include/leveldb/db.h
leveldb/include/leveldb/env.h
leveldb/include/leveldb/filter_policy.h
leveldb/include/leveldb/iterator.h
leveldb/include/leveldb/options.h
leveldb/include/leveldb/slice.h
leveldb/include/leveldb/status.h
leveldb/include/leveldb/table.h
leveldb/include/leveldb/table_builder.h
leveldb/include/leveldb/write_batch.h
leveldb/port/atomic_pointer.h
leveldb/port/port.h
